AllowableStress/AllowableStress.py
AllowableStress/__init__.py
allowablestress-0.0.3.dist-info/licenses/LICENSE
allowablestress-0.0.3.dist-info/METADATA
allowablestress-0.0.3.dist-info/WHEEL
allowablestress-0.0.3.dist-info/top_level.txt
allowablestress-0.0.3.dist-info/RECORD
